{
	"name": "relationship-tdtzctyrcg",
	"properties": {
		"Namespace": {
			"DatabaseName": "OilGas_76m"
		},
		"Origin": {
			"Type": "SPARK"
		},
		"FromTableName": "Employee",
		"ToTableName": "Transaction",
		"ColumnRelationshipInformations": [
			{
				"FromColumnName": "EmployeeId",
				"ToColumnName": "ApprovedByEmployeeId"
			}
		],
		"Properties": {
			"DerivedModelRelationshipInfo": "{\"baseRelationship\":{\"fromEntity\":\"Employee.cdm.json/Employee\",\"toEntity\":\"Transaction.cdm.json/Transaction\",\"joinPairs\":[{\"fromAttribute\":\"EmployeeId\",\"toAttribute\":\"ApprovedByEmployeeId\"}]}}"
		},
		"PublishStatus": "PUBLISHED",
		"ObjectVersion": 1,
		"ObjectId": "15185966-95e0-49b2-8fd8-a59b1277f56b",
		"Name": "relationship-tdtzctyrcg",
		"EntityType": "RELATIONSHIP"
	},
	"type": "RELATIONSHIP"
}